setup.py
tinycms_menu/__init__.py
tinycms_menu/admin.py
tinycms_menu/models.py
tinycms_menu/tests.py
tinycms_menu.egg-info/PKG-INFO
tinycms_menu.egg-info/SOURCES.txt
tinycms_menu.egg-info/dependency_links.txt
tinycms_menu.egg-info/entry_points.txt
tinycms_menu.egg-info/not-zip-safe
tinycms_menu.egg-info/requires.txt
tinycms_menu.egg-info/top_level.txt
tinycms_menu/migrations/0001_initial.py
tinycms_menu/migrations/__init__.py
tinycms_menu/templatetags/__init__.py
tinycms_menu/templatetags/tinycms_menu_tags.py