Metadata-Version: 1.1
Name: tinycms-menu
Version: 0.1.1
Summary: Menu addon for tinycms
Home-page: https://www.whiteblack-cat.info/
Author: ccat
Author-email: UNKNOWN
License: MIT
Platform: UNKNOWN
Classifier: Framework :: Django
Classifier: License :: OSI Approved :: MIT License
Classifier: Programming Language :: Python
